glycontact/__init__.py
glycontact/learning.py
glycontact/lwca.py
glycontact/process.py
glycontact/visualize.py
glycontact/20250516_GLYCOSHAPE.json
glycontact/glycan_graphs.pkl
glycontact/unilectin_data.json
glycontact-0.3.0.dist-info/METADATA
glycontact-0.3.0.dist-info/WHEEL
glycontact-0.3.0.dist-info/licenses/LICENSE
glycontact-0.3.0.dist-info/RECORD
