Metadata-Version: 2.4
Name: glycontact
Version: 0.3.0
Summary: A Python package for processing and analyzing glycan 3D structures
Project-URL: Homepage, https://github.com/lthomes/glycontact
Project-URL: Repository, https://github.com/lthomes/glycontact
Project-URL: Documentation, https://github.com/lthomes/glycontact#readme
Author-email: Luc Thomes <luc.thomes@univ-lille.fr>
License: MIT License
License-File: LICENSE
Keywords: PDB,bioinformatics,glycans,structural biology
Classifier: Development Status :: 3 - Alpha
Classifier: Intended Audience :: Science/Research
Classifier: License :: OSI Approved :: MIT License
Classifier: Programming Language :: Python :: 3
Classifier: Programming Language :: Python :: 3.9
Classifier: Programming Language :: Python :: 3.10
Classifier: Programming Language :: Python :: 3.11
Classifier: Programming Language :: Python :: 3.12
Classifier: Topic :: Scientific/Engineering :: Bio-Informatics
Requires-Python: >=3.9
Requires-Dist: glycowork>=1.6
Requires-Dist: imageio
Requires-Dist: mdtraj
Requires-Dist: plotly
Requires-Dist: py3dmol
Requires-Dist: requests
Requires-Dist: scikit-learn
Requires-Dist: tqdm
Provides-Extra: ml
Requires-Dist: torch-geometric>=2.3.0; extra == 'ml'
Requires-Dist: torch>=2.0.0; extra == 'ml'
